resume_pycli/__init__.py
resume_pycli/__main__.py
resume_pycli/cli.py
resume_pycli/html.py
resume_pycli/pdf.py
resume_pycli/resume.json
resume_pycli/schema.json
resume_pycli/themes/base/index.html
resume_pycli/themes/flat/LICENSE
resume_pycli/themes/flat/index.html
resume_pycli/themes/flat/static/bootstrap/css/bootstrap-theme.css
resume_pycli/themes/flat/static/bootstrap/css/bootstrap-theme.css.map
resume_pycli/themes/flat/static/bootstrap/css/bootstrap-theme.min.css
resume_pycli/themes/flat/static/bootstrap/css/bootstrap-theme.min.css.map
resume_pycli/themes/flat/static/bootstrap/css/bootstrap.css
resume_pycli/themes/flat/static/bootstrap/css/bootstrap.css.map
resume_pycli/themes/flat/static/bootstrap/css/bootstrap.min.css
resume_pycli/themes/flat/static/bootstrap/css/bootstrap.min.css.map
resume_pycli/themes/flat/static/bootstrap/fonts/glyphicons-halflings-regular.eot
resume_pycli/themes/flat/static/bootstrap/fonts/glyphicons-halflings-regular.svg
resume_pycli/themes/flat/static/bootstrap/fonts/glyphicons-halflings-regular.ttf
resume_pycli/themes/flat/static/bootstrap/fonts/glyphicons-halflings-regular.woff
resume_pycli/themes/flat/static/bootstrap/fonts/glyphicons-halflings-regular.woff2
resume_pycli/themes/flat/static/bootstrap/js/bootstrap.js
resume_pycli/themes/flat/static/bootstrap/js/bootstrap.min.js
resume_pycli/themes/flat/static/bootstrap/js/npm.js
resume_pycli/themes/flat/static/octicons/octicons-local.eot
resume_pycli/themes/flat/static/octicons/octicons.eot
resume_pycli/themes/flat/static/octicons/octicons.min.css
resume_pycli/themes/flat/static/octicons/octicons.svg
resume_pycli/themes/flat/static/octicons/octicons.ttf
resume_pycli/themes/flat/static/octicons/octicons.woff
resume_pycli/themes/flat/style.css
resume_pycli/themes/stackoverflow/LICENSE
resume_pycli/themes/stackoverflow/index.html
resume_pycli/themes/stackoverflow/partials/awards.html
resume_pycli/themes/stackoverflow/partials/basics.html
resume_pycli-4.1.1.dist-info/METADATA
resume_pycli-4.1.1.dist-info/entry_points.txt
resume_pycli-4.1.1.dist-info/WHEEL
resume_pycli-4.1.1.dist-info/LICENSE
resume_pycli-4.1.1.dist-info/RECORD
