Metadata-Version: 2.1
Name: resume-pycli
Version: 4.1.1
Summary: CLI tool to easily setup a new resume
Home-page: https://github.com/nikaro/resume-pycli
License: GPL-3.0-or-later
Keywords: resume,json,cli
Author: Nicolas Karolak
Author-email: nicolas@karolak.fr
Requires-Python: >=3.9,<4.0
Classifier: License :: OSI Approved :: GNU General Public License v3 or later (GPLv3+)
Classifier: Programming Language :: Python :: 3
Classifier: Programming Language :: Python :: 3.9
Classifier: Programming Language :: Python :: 3.10
Classifier: Programming Language :: Python :: 3.11
Provides-Extra: playwright
Provides-Extra: weasyprint
Requires-Dist: beautifulsoup4
Requires-Dist: flask
Requires-Dist: jsonschema
Requires-Dist: playwright ; extra == "playwright"
Requires-Dist: typer[all]
Requires-Dist: weasyprint ; extra == "weasyprint"
Project-URL: Repository, https://github.com/nikaro/resume-pycli
